gxr_py_pkg_temp/__init__.py
gxr_py_pkg_temp/moduleA.py
gxr_py_pkg_temp-0.0.2.dist-info/METADATA
gxr_py_pkg_temp-0.0.2.dist-info/WHEEL
gxr_py_pkg_temp-0.0.2.dist-info/top_level.txt
gxr_py_pkg_temp-0.0.2.dist-info/RECORD
