Metadata-Version: 2.1
Name: gxr-py-pkg-temp
Version: 0.0.2
Summary: description
Home-page: https://github.com/gxr404/py-pkg-template
Author: gxr404
Author-email: gxr40404@gmail.com
License: UNKNOWN
Platform: UNKNOWN
Classifier: Programming Language :: Python :: 3
Classifier: License :: OSI Approved :: MIT License
Classifier: Operating System :: OS Independent
Requires-Python: >=3.6
